request_tea_ok/main_module.py
request_tea_ok-1.0.3.dist-info/LICENSE
request_tea_ok-1.0.3.dist-info/METADATA
request_tea_ok-1.0.3.dist-info/WHEEL
request_tea_ok-1.0.3.dist-info/entry_points.txt
request_tea_ok-1.0.3.dist-info/top_level.txt
request_tea_ok-1.0.3.dist-info/RECORD
